fkart/__init__.py
fkart/flipkart.py
fkart-0.0.1.dist-info/METADATA
fkart-0.0.1.dist-info/WHEEL
fkart-0.0.1.dist-info/top_level.txt
fkart-0.0.1.dist-info/RECORD
